slock/__init__.py
slock/cli/__init__.py
slock/cli/cli.py
slock/core/__init__.py
slock/core/crypto.py
slock/core/dependency.py
slock/core/importer.py
slock/utils/__init__.py
sloth_lock-0.2.0.dist-info/METADATA
sloth_lock-0.2.0.dist-info/WHEEL
sloth_lock-0.2.0.dist-info/entry_points.txt
sloth_lock-0.2.0.dist-info/top_level.txt
sloth_lock-0.2.0.dist-info/RECORD
