Metadata-Version: 2.4
Name: sloth-lock
Version: 0.2.0
Summary: 파일 암호화/복호화 도구 (File Encryption/Decryption Tool)
Home-page: https://github.com/cryingmiso/slock
Author: cryingmiso
Author-email: if.sloth@gmail.com
Classifier: Programming Language :: Python :: 3
Classifier: License :: OSI Approved :: MIT License
Classifier: Operating System :: OS Independent
Classifier: Natural Language :: Korean
Classifier: Natural Language :: English
Classifier: Topic :: Security :: Cryptography
Requires-Python: >=3.6
Requires-Dist: cryptography>=42.0.0
Requires-Dist: click>=8.1.7
Requires-Dist: astroid>=2.15.0
Dynamic: author
Dynamic: author-email
Dynamic: classifier
Dynamic: description
Dynamic: description-content-type
Dynamic: home-page
Dynamic: requires-dist
Dynamic: requires-python
Dynamic: summary
